parkapi_sources/__init__.py
parkapi_sources/_version.py
parkapi_sources/exceptions.py
parkapi_sources/parkapi_sources.py
parkapi_sources/converters/__init__.py
parkapi_sources/converters/aachen/__init__.py
parkapi_sources/converters/aachen/converter.py
parkapi_sources/converters/aalen/__init__.py
parkapi_sources/converters/aalen/converter.py
parkapi_sources/converters/aalen/models.py
parkapi_sources/converters/apcoa/__init__.py
parkapi_sources/converters/apcoa/converter.py
parkapi_sources/converters/apcoa/mapper.py
parkapi_sources/converters/apcoa/validators.py
parkapi_sources/converters/bahn_v2/__init__.py
parkapi_sources/converters/bahn_v2/converter.py
parkapi_sources/converters/bahn_v2/mapper.py
parkapi_sources/converters/bahn_v2/validators.py
parkapi_sources/converters/base_converter/__init__.py
parkapi_sources/converters/base_converter/base_converter.py
parkapi_sources/converters/base_converter/datex2/__init__.py
parkapi_sources/converters/base_converter/datex2/datex2_realtime_mixin.py
parkapi_sources/converters/base_converter/datex2/datex2_static_mixin.py
parkapi_sources/converters/base_converter/datex2/parking_facility_mixin.py
parkapi_sources/converters/base_converter/datex2/parking_facility_validator.py
parkapi_sources/converters/base_converter/datex2/parking_record_status_mixin.py
parkapi_sources/converters/base_converter/datex2/parking_record_status_validator.py
parkapi_sources/converters/base_converter/datex2/urban_parking_site_mixin.py
parkapi_sources/converters/base_converter/datex2/urban_parking_site_validator.py
parkapi_sources/converters/base_converter/pull/__init__.py
parkapi_sources/converters/base_converter/pull/mobilithek_parking_site_pull_converter.py
parkapi_sources/converters/base_converter/pull/mobilithek_pull_converter.py
parkapi_sources/converters/base_converter/pull/pull_converter.py
parkapi_sources/converters/base_converter/pull/pull_scraper_mixin.py
parkapi_sources/converters/base_converter/pull/static_geojson_mixin.py
parkapi_sources-0.33.3.dist-info/licenses/LICENCE.txt
parkapi_sources-0.33.3.dist-info/METADATA
parkapi_sources-0.33.3.dist-info/WHEEL
parkapi_sources-0.33.3.dist-info/top_level.txt
parkapi_sources-0.33.3.dist-info/RECORD
