Metadata-Version: 2.4
Name: parkapi_sources
Version: 0.33.3
Summary: ParkAPI Sources is a collection of converters from several different data sources to normalized ParkAPI data.
Author-email: "Ernesto Ruge, binary butterfly GmbH" <ernesto.ruge@binary-butterfly.de>
Maintainer-email: "Ernesto Ruge, binary butterfly GmbH" <ernesto.ruge@binary-butterfly.de>
Project-URL: Homepage, https://github.com/ParkenDD/parkapi-sources-v3
Project-URL: Repository, https://github.com/ParkenDD/parkapi-sources-v3.git
Project-URL: Issues, https://github.com/ParkenDD/parkapi-sources-v3/issues
Project-URL: Changelog, https://github.com/ParkenDD/parkapi-sources-v3/blob/main/CHANGELOG.md
Keywords: data,parking,converter,mobility,car,bike
Classifier: Development Status :: 3 - Alpha
Classifier: Intended Audience :: Developers
Classifier: License :: OSI Approved :: MIT License
Classifier: Operating System :: OS Independent
Classifier: Programming Language :: Python :: 3
Classifier: Programming Language :: Python :: 3.12
Classifier: Programming Language :: Python :: 3.13
Classifier: Programming Language :: Python :: Implementation :: CPython
Classifier: Topic :: Software Development :: Libraries :: Python Modules
Classifier: Topic :: Utilities
Requires-Python: >=3.12
License-File: LICENCE.txt
Requires-Dist: validataclass~=0.11.0
Requires-Dist: pyproj~=3.7.2
Requires-Dist: lxml~=6.0.2
Requires-Dist: openpyxl~=3.1.5
Requires-Dist: requests~=2.32.5
Requires-Dist: beautifulsoup4~=4.14.3
Requires-Dist: urllib3~=2.6.2
Requires-Dist: isodate~=0.7.2
Requires-Dist: shapely~=2.1.2
Requires-Dist: opening-hours-py~=1.1.5
Provides-Extra: testing
Requires-Dist: ruff~=0.14.10; extra == "testing"
Requires-Dist: pytest~=9.0.2; extra == "testing"
Requires-Dist: pytest-cov~=7.0.0; extra == "testing"
Requires-Dist: requests-mock~=1.12.1; extra == "testing"
Dynamic: license-file
